pinder/core/__init__.py
pinder/core/_version.py
pinder/core/index/__init__.py
pinder/core/index/id.py
pinder/core/index/system.py
pinder/core/index/utils.py
pinder/core/loader/__init__.py
pinder/core/loader/dataset.py
pinder/core/loader/filters.py
pinder/core/loader/geodata.py
pinder/core/loader/loader.py
pinder/core/loader/structure.py
pinder/core/loader/transforms.py
pinder/core/loader/utils.py
pinder/core/loader/writer.py
pinder/core/structure/__init__.py
pinder/core/structure/atoms.py
pinder/core/structure/contacts.py
pinder/core/structure/models.py
pinder/core/structure/superimpose.py
pinder/core/structure/surgery.py
pinder/core/submit/__init__.py
pinder/core/utils/__init__.py
pinder/core/utils/cloud.py
pinder/core/utils/constants.py
pinder/core/utils/dataclass.py
pinder/core/utils/log.py
pinder/core/utils/paths.py
pinder/core/utils/pdb_utils.py
pinder/core/utils/process.py
pinder/core/utils/retry.py
pinder/core/utils/string.py
pinder/core/utils/timer.py
pinder/core/utils/unbound.py
pinder/data/README.md
pinder/data/__init__.py
pinder/data/_version.py
pinder/data/alignment_utils.py
pinder/data/apo_utils.py
pinder/data/config.py
pinder/data/csv_utils.py
pinder/data/find_transitive_hits.py
pinder/data/foldseek_utils.py
pinder/data/get_alignment_similarity.py
pinder/data/get_annotations.py
pinder/data/get_apo.py
pinder/data/get_clusters.py
pinder/data/get_data.py
pinder/data/get_dimers.py
pinder/data/get_splits.py
pinder/data/get_test_set.py
pinder/data/graph_utils.py
pinder/data/rcsb_rsync.py
pinder/data/run.py
pinder/data/system.py
pinder/data/annotation/__init__.py
pinder/data/annotation/canonical_apo.py
pinder/data/annotation/constants.py
pinder/data/annotation/contact_classification.py
pinder/data/annotation/detached_components.py
pinder/data/annotation/elongation.py
pinder/data/annotation/graphql.py
pinder/data/annotation/interface_gaps.py
pinder/data/annotation/planarity.py
pinder/data/annotation/sabdab.py
pinder/data/pipeline/__init__.py
pinder-0.5.0.dist-info/LICENSE
pinder-0.5.0.dist-info/METADATA
pinder-0.5.0.dist-info/WHEEL
pinder-0.5.0.dist-info/entry_points.txt
pinder-0.5.0.dist-info/top_level.txt
pinder-0.5.0.dist-info/RECORD
