Metadata-Version: 2.1
Name: pinder
Version: 0.5.0
Summary: PINDER: The Protein INteraction Dataset and Evaluation Resource
Project-URL: Homepage, https://github.com/pinder-org/pinder
Project-URL: Issues, https://github.com/pinder-org/pinder/issues
Classifier: Programming Language :: Python :: 3
Classifier: License :: OSI Approved :: Apache Software License
Classifier: Operating System :: OS Independent
Requires-Python: >=3.10
License-File: LICENSE
Requires-Dist: biotite >=1.0
Requires-Dist: fastpdb
Requires-Dist: numpy <2
Requires-Dist: pandas
Requires-Dist: pyarrow >=12.0
Requires-Dist: torch
Requires-Dist: torchtyping
Requires-Dist: typeguard ==2.13.3
Requires-Dist: typing-extensions
Requires-Dist: pydantic >=2.0
Requires-Dist: tqdm
Requires-Dist: plotly
Requires-Dist: nbformat
Requires-Dist: google-cloud-storage
Requires-Dist: gcsfs
Requires-Dist: torch-geometric
Requires-Dist: tabulate
Requires-Dist: PyYAML
Requires-Dist: scikit-learn
Provides-Extra: data
Requires-Dist: fire ; extra == 'data'
Requires-Dist: gemmi ; extra == 'data'
Requires-Dist: networkx ; extra == 'data'
Requires-Dist: scikit-learn <=1.2.2 ; extra == 'data'
Requires-Dist: python-graphql-client ; extra == 'data'
Requires-Dist: mpire ; extra == 'data'
Requires-Dist: matplotlib ; extra == 'data'
Requires-Dist: seaborn ; extra == 'data'
Requires-Dist: colormath ; extra == 'data'
Provides-Extra: datapy312
Requires-Dist: fire ; extra == 'datapy312'
Requires-Dist: gemmi ; extra == 'datapy312'
Requires-Dist: networkx ; extra == 'datapy312'
Requires-Dist: scikit-learn ; extra == 'datapy312'
Requires-Dist: python-graphql-client ; extra == 'datapy312'
Requires-Dist: mpire ; extra == 'datapy312'
Requires-Dist: matplotlib ; extra == 'datapy312'
Requires-Dist: seaborn ; extra == 'datapy312'
Requires-Dist: colormath ; extra == 'datapy312'
Provides-Extra: dev
Requires-Dist: pinder[data,leaderboard,lint,test,type] ; extra == 'dev'
Provides-Extra: docs
Requires-Dist: jupyter-sphinx ; extra == 'docs'
Requires-Dist: sphinxcontrib-applehelp ; extra == 'docs'
Requires-Dist: sphinxcontrib-bibtex ; extra == 'docs'
Requires-Dist: sphinxcontrib-devhelp ; extra == 'docs'
Requires-Dist: sphinxcontrib-htmlhelp ; extra == 'docs'
Requires-Dist: sphinxcontrib-jquery ; extra == 'docs'
Requires-Dist: sphinxcontrib-jsmath ; extra == 'docs'
Requires-Dist: sphinxcontrib-qthelp ; extra == 'docs'
Requires-Dist: sphinxcontrib-serializinghtml ; extra == 'docs'
Requires-Dist: sphinx-copybutton ; extra == 'docs'
Requires-Dist: sphinx-design ; extra == 'docs'
Requires-Dist: jupyterlab-myst ; extra == 'docs'
Requires-Dist: myst-nb ; extra == 'docs'
Requires-Dist: myst-parser[linkify] ; extra == 'docs'
Requires-Dist: jupytext ; extra == 'docs'
Requires-Dist: pydata-sphinx-theme ; extra == 'docs'
Requires-Dist: numpydoc ; extra == 'docs'
Provides-Extra: leaderboard
Requires-Dist: quarto-cli ; extra == 'leaderboard'
Requires-Dist: itables ; extra == 'leaderboard'
Requires-Dist: matplotlib ; extra == 'leaderboard'
Requires-Dist: seaborn ; extra == 'leaderboard'
Provides-Extra: lint
Requires-Dist: ruff ==0.4.9 ; extra == 'lint'
Requires-Dist: pre-commit ==3.6.0 ; extra == 'lint'
Provides-Extra: test
Requires-Dist: tox >=4 ; extra == 'test'
Requires-Dist: pytest ==7.2.0 ; extra == 'test'
Requires-Dist: pytest-cov ==4.0.0 ; extra == 'test'
Requires-Dist: build ==0.9.0 ; extra == 'test'
Requires-Dist: setuptools-scm[toml] ==7.0.5 ; extra == 'test'
Provides-Extra: type
Requires-Dist: mypy ==1.10.0 ; extra == 'type'
Requires-Dist: pydantic ; extra == 'type'
Requires-Dist: types-PyYAML ; extra == 'type'
Requires-Dist: types-requests ; extra == 'type'
